{
  "cols": [
        {"id":"","label":"Date","type":"date"},
        {"id":"","label":"MilDiff","type":"number"},
		{"id":"","label":"MinDiff","type":"number"},
		{"id":"","label":"MilTgt","type":"number"},
		{"id":"","label":"MinTgt","type":"number"}
      ],
  "rows": [
		{"c":[{"v":"Date(2015,3,6)", "f":"4/6"},{"v":-1,"f":null},{"v":-1,"f":null},{"v":0.5,"f":null},{"v":0.5,"f":null}]},
{"c":[{"v":"Date(2015,3,7)", "f":"4/7"},{"v":-2,"f":null},{"v":-1,"f":null},{"v":0.5,"f":null},{"v":0.5,"f":null}]},
{"c":[{"v":"Date(2015,3,8)", "f":"4/8"},{"v":-3,"f":null},{"v":-2,"f":null},{"v":0.5,"f":null},{"v":0.5,"f":null}]},
{"c":[{"v":"Date(2015,3,9)", "f":"4/9"},{"v":-3,"f":null},{"v":-3,"f":null},{"v":0.5,"f":null},{"v":0.5,"f":null}]},
{"c":[{"v":"Date(2015,3,10)", "f":"4/10"},{"v":-4,"f":null},{"v":-2,"f":null},{"v":0.5,"f":null},{"v":0.5,"f":null}]},
{"c":[{"v":"Date(2015,3,11)", "f":"4/11"},{"v":-3,"f":null},{"v":-3,"f":null},{"v":0.5,"f":null},{"v":0.5,"f":null}]},
{"c":[{"v":"Date(2015,3,12)", "f":"4/12"},{"v":-4,"f":null},{"v":-4,"f":null},{"v":0.5,"f":null},{"v":0.5,"f":null}]},
{"c":[{"v":"Date(2015,3,13)", "f":"4/13"},{"v":-3,"f":null},{"v":-5,"f":null},{"v":0.5,"f":null},{"v":0.5,"f":null}]},
{"c":[{"v":"Date(2015,3,15)", "f":"4/15"},{"v":-4,"f":null},{"v":-4,"f":null},{"v":0.5,"f":null},{"v":0.5,"f":null}]},
{"c":[{"v":"Date(2015,3,16)", "f":"4/16"},{"v":-5,"f":null},{"v":-3,"f":null},{"v":0.5,"f":null},{"v":0.5,"f":null}]},
{"c":[{"v":"Date(2015,3,17)", "f":"4/17"},{"v":-6,"f":null},{"v":-2,"f":null},{"v":0.5,"f":null},{"v":0.5,"f":null}]},
{"c":[{"v":"Date(2015,3,18)", "f":"4/18"},{"v":-7,"f":null},{"v":-3,"f":null},{"v":0.5,"f":null},{"v":0.5,"f":null}]},
{"c":[{"v":"Date(2015,3,19)", "f":"4/19"},{"v":-8,"f":null},{"v":-2,"f":null},{"v":0.5,"f":null},{"v":0.5,"f":null}]},
{"c":[{"v":"Date(2015,3,20)", "f":"4/20"},{"v":-9,"f":null},{"v":-3,"f":null},{"v":0.5,"f":null},{"v":0.5,"f":null}]},
{"c":[{"v":"Date(2015,3,21)", "f":"4/21"},{"v":-10,"f":null},{"v":-4,"f":null},{"v":0.5,"f":null},{"v":0.5,"f":null}]},
{"c":[{"v":"Date(2015,3,22)", "f":"4/22"},{"v":-11,"f":null},{"v":-3,"f":null},{"v":0.5,"f":null},{"v":0.5,"f":null}]},
{"c":[{"v":"Date(2015,3,23)", "f":"4/23"},{"v":-10,"f":null},{"v":-3,"f":null},{"v":0.5,"f":null},{"v":0.5,"f":null}]},
{"c":[{"v":"Date(2015,3,24)", "f":"4/24"},{"v":-11,"f":null},{"v":-4,"f":null},{"v":0.5,"f":null},{"v":0.5,"f":null}]},
{"c":[{"v":"Date(2015,3,25)", "f":"4/25"},{"v":-12,"f":null},{"v":-3,"f":null},{"v":0.5,"f":null},{"v":0.5,"f":null}]},
{"c":[{"v":"Date(2015,3,26)", "f":"4/26"},{"v":-11,"f":null},{"v":-2,"f":null},{"v":0.5,"f":null},{"v":0.5,"f":null}]},
{"c":[{"v":"Date(2015,3,27)", "f":"4/27"},{"v":-12,"f":null},{"v":-3,"f":null},{"v":0.5,"f":null},{"v":0.5,"f":null}]},
{"c":[{"v":"Date(2015,3,28)", "f":"4/28"},{"v":-13,"f":null},{"v":-2,"f":null},{"v":0.5,"f":null},{"v":0.5,"f":null}]},
{"c":[{"v":"Date(2015,3,29)", "f":"4/29"},{"v":-12,"f":null},{"v":-3,"f":null},{"v":0.5,"f":null},{"v":0.5,"f":null}]},
{"c":[{"v":"Date(2015,3,30)", "f":"4/30"},{"v":-12,"f":null},{"v":-2,"f":null},{"v":0.5,"f":null},{"v":0.5,"f":null}]},
{"c":[{"v":"Date(2015,4,1)", "f":"5/1"},{"v":-13,"f":null},{"v":-1,"f":null},{"v":0.5,"f":null},{"v":0.5,"f":null}]},
{"c":[{"v":"Date(2015,4,2)", "f":"5/2"},{"v":-12,"f":null},{"v":0,"f":null},{"v":0.5,"f":null},{"v":0.5,"f":null}]},
{"c":[{"v":"Date(2015,4,3)", "f":"5/3"},{"v":-11,"f":null},{"v":1,"f":null},{"v":0.5,"f":null},{"v":0.5,"f":null}]},
{"c":[{"v":"Date(2015,4,4)", "f":"5/4"},{"v":-10,"f":null},{"v":2,"f":null},{"v":0.5,"f":null},{"v":0.5,"f":null}]},
{"c":[{"v":"Date(2015,4,5)", "f":"5/5"},{"v":-11,"f":null},{"v":1,"f":null},{"v":0.5,"f":null},{"v":6.5,"f":null}]},
{"c":[{"v":"Date(2015,4,6)", "f":"5/6"},{"v":-10,"f":null},{"v":2,"f":null},{"v":0.5,"f":null},{"v":6.5,"f":null}]},
{"c":[{"v":"Date(2015,4,7)", "f":"5/7"},{"v":-11,"f":null},{"v":3,"f":null},{"v":0.5,"f":null},{"v":6.5,"f":null}]},
{"c":[{"v":"Date(2015,4,8)", "f":"5/8"},{"v":-12,"f":null},{"v":4,"f":null},{"v":0.5,"f":null},{"v":6.5,"f":null}]},
{"c":[{"v":"Date(2015,4,9)", "f":"5/9"},{"v":-11,"f":null},{"v":5,"f":null},{"v":0.5,"f":null},{"v":6.5,"f":null}]},
{"c":[{"v":"Date(2015,4,10)", "f":"5/10"},{"v":-10,"f":null},{"v":4,"f":null},{"v":0.5,"f":null},{"v":6.5,"f":null}]},
{"c":[{"v":"Date(2015,4,11)", "f":"5/11"},{"v":-9,"f":null},{"v":4,"f":null},{"v":0.5,"f":null},{"v":6.5,"f":null}]},
{"c":[{"v":"Date(2015,4,12)", "f":"5/12"},{"v":-10,"f":null},{"v":3,"f":null},{"v":0.5,"f":null},{"v":6.5,"f":null}]},
{"c":[{"v":"Date(2015,4,13)", "f":"5/13"},{"v":-11,"f":null},{"v":4,"f":null},{"v":0.5,"f":null},{"v":6.5,"f":null}]},
{"c":[{"v":"Date(2015,4,14)", "f":"5/14"},{"v":-11,"f":null},{"v":3,"f":null},{"v":0.5,"f":null},{"v":6.5,"f":null}]},
{"c":[{"v":"Date(2015,4,15)", "f":"5/15"},{"v":-10,"f":null},{"v":4,"f":null},{"v":0.5,"f":null},{"v":6.5,"f":null}]},
{"c":[{"v":"Date(2015,4,16)", "f":"5/16"},{"v":-11,"f":null},{"v":5,"f":null},{"v":0.5,"f":null},{"v":6.5,"f":null}]},
{"c":[{"v":"Date(2015,4,17)", "f":"5/17"},{"v":-12,"f":null},{"v":4,"f":null},{"v":0.5,"f":null},{"v":6.5,"f":null}]},
{"c":[{"v":"Date(2015,4,18)", "f":"5/18"},{"v":-11,"f":null},{"v":4,"f":null},{"v":0.5,"f":null},{"v":6.5,"f":null}]},
{"c":[{"v":"Date(2015,4,19)", "f":"5/19"},{"v":-10,"f":null},{"v":5,"f":null},{"v":0.5,"f":null},{"v":6.5,"f":null}]},
{"c":[{"v":"Date(2015,4,20)", "f":"5/20"},{"v":-11,"f":null},{"v":6,"f":null},{"v":0.5,"f":null},{"v":6.5,"f":null}]},
{"c":[{"v":"Date(2015,4,21)", "f":"5/21"},{"v":-12,"f":null},{"v":6,"f":null},{"v":0.5,"f":null},{"v":6.5,"f":null}]},
{"c":[{"v":"Date(2015,4,22)", "f":"5/22"},{"v":-11,"f":null},{"v":5,"f":null},{"v":0.5,"f":null},{"v":6.5,"f":null}]},
{"c":[{"v":"Date(2015,4,23)", "f":"5/23"},{"v":-12,"f":null},{"v":6,"f":null},{"v":0.5,"f":null},{"v":6.5,"f":null}]},
{"c":[{"v":"Date(2015,4,24)", "f":"5/24"},{"v":-13,"f":null},{"v":7,"f":null},{"v":0.5,"f":null},{"v":6.5,"f":null}]},
{"c":[{"v":"Date(2015,4,25)", "f":"5/25"},{"v":-14,"f":null},{"v":8,"f":null},{"v":0.5,"f":null},{"v":6.5,"f":null}]},
{"c":[{"v":"Date(2015,4,26)", "f":"5/26"},{"v":-15,"f":null},{"v":9,"f":null},{"v":0.5,"f":null},{"v":6.5,"f":null}]}
      ]
}